paker/__init__.py
paker/__main__.py
paker/exceptions.py
paker/utils.py
paker/importers/__init__.py
paker/importers/_tempimporter.py
paker/importers/jsonimporter.py
paker-0.6.0.dist-info/LICENSE
paker-0.6.0.dist-info/METADATA
paker-0.6.0.dist-info/WHEEL
paker-0.6.0.dist-info/entry_points.txt
paker-0.6.0.dist-info/top_level.txt
paker-0.6.0.dist-info/RECORD
