Metadata-Version: 2.1
Name: paker
Version: 0.6.0
Summary: Import Python modules from JSON documents
Home-page: https://github.com/desty2k/paker
Author: Wojciech Wentland
Author-email: wojciech.wentland@int.pl
License: MIT
Keywords: import,loader,finder,importer,json,memory,memimporter
Platform: UNKNOWN
Classifier: Development Status :: 4 - Beta
Classifier: Environment :: Console
Classifier: License :: OSI Approved :: MIT License
Classifier: Programming Language :: Python :: 3.6
Classifier: Programming Language :: Python :: 3.7
Classifier: Programming Language :: Python :: 3.8
Classifier: Programming Language :: Python :: 3.9
Classifier: Programming Language :: Python :: Implementation :: CPython
Classifier: Programming Language :: Python :: Implementation :: PyPy
Classifier: Intended Audience :: Developers
Classifier: Intended Audience :: Information Technology
Classifier: Topic :: Software Development :: Libraries :: Python Modules
Classifier: Topic :: Software Development :: Build Tools
Classifier: Topic :: Software Development :: Testing
Requires-Python: >=3.6
License-File: LICENSE
